cast.py
setup.py
cast.egg-info/PKG-INFO
cast.egg-info/SOURCES.txt
cast.egg-info/dependency_links.txt
cast.egg-info/entry_points.txt
cast.egg-info/not-zip-safe
cast.egg-info/requires.txt
cast.egg-info/top_level.txt