Metadata-Version: 1.1
Name: cast
Version: 0.1.1
Summary: Command line utility to control your Google Chromecast.
Home-page: https://github.com/jaapz/cast
Author: Jaap Broekhuizen
Author-email: jaapz.b@gmail.com
License: MIT
Platform: any
Classifier: License :: OSI Approved :: MIT License
Classifier: Programming Language :: Python
Classifier: Operating System :: POSIX
